LICENSE
MANIFEST.in
README.md
json_schema_to_class.py
requirements.txt
setup.py
json_schema_to_class.egg-info/PKG-INFO
json_schema_to_class.egg-info/SOURCES.txt
json_schema_to_class.egg-info/dependency_links.txt
json_schema_to_class.egg-info/entry_points.txt
json_schema_to_class.egg-info/requires.txt
json_schema_to_class.egg-info/top_level.txt