Metadata-Version: 2.1
Name: json-schema-to-class
Version: 0.2.1
Summary: Convert JSON Schema into Python Class
Home-page: https://github.com/FebruaryBreeze/json-schema-to-class
Author: SF-Zhou
Author-email: sfzhou.scut@gmail.com
License: MIT
Keywords: JSON Schema Class
Platform: UNKNOWN
Requires-Python: >=3.6.0
